ndx_photometry/__init__.py
ndx_photometry/photometry.py
ndx_photometry/spec/ndx-photometry.extensions.yaml
ndx_photometry/spec/ndx-photometry.namespace.yaml
tests/__init__.py
tests/integration/__init__.py
tests/integration/test_photometry.py
tests/unit/__init__.py
tests/unit/test_fibers_table.py
tests/unit/test_photometry.py
ndx_photometry-0.4.0.dist-info/LICENSE.txt
ndx_photometry-0.4.0.dist-info/METADATA
ndx_photometry-0.4.0.dist-info/WHEEL
ndx_photometry-0.4.0.dist-info/top_level.txt
ndx_photometry-0.4.0.dist-info/RECORD
