Metadata-Version: 2.1
Name: ndx-photometry
Version: 0.4.0
Summary: extension for fiber photometry data
Home-page: https://github.com/catalystneuro/ndx-photometry
Author: Ben Dichter, Akshay Jaggi
Author-email: ben.dichter@catalystneuro.com
License: BSD 3-Clause
Classifier: Intended Audience :: Developers
Classifier: Intended Audience :: Science/Research
License-File: LICENSE.txt
Requires-Dist: pynwb >=1.3.0
Requires-Dist: numpy >=1.22.0
Requires-Dist: h5py
